setup.py
cs_distributions/Binomialdistribution.py
cs_distributions/Gaussiandistribution.py
cs_distributions/Generaldistribution.py
cs_distributions/__init__.py
cs_distributions.egg-info/PKG-INFO
cs_distributions.egg-info/SOURCES.txt
cs_distributions.egg-info/dependency_links.txt
cs_distributions.egg-info/not-zip-safe
cs_distributions.egg-info/top_level.txt